person_analyser_tool_database_models/__init__.py
person_analyser_tool_database_models/alembic/env.py
person_analyser_tool_database_models/alembic/README
person_analyser_tool_database_models/alembic/script.py.mako
person_analyser_tool_database_models/alembic/versions/71f62e961e40_add_box_and_line_analytics_tables.py
person_analyser_tool_database_models/alembic.ini
person_analyser_tool_database_models/tables/__init__.py
person_analyser_tool_database_models/tables/base.py
person_analyser_tool_database_models/tables/box_analytics.py
person_analyser_tool_database_models/tables/line_analytics.py
person_analyser_tool_database_models-0.1.0.dist-info/METADATA
person_analyser_tool_database_models-0.1.0.dist-info/WHEEL
person_analyser_tool_database_models-0.1.0.dist-info/RECORD
