Metadata-Version: 2.1
Name: person-analyser-tool-database-models
Version: 0.1.0
Summary: 
Author: Pintér Tamás
Author-email: tamas.pinter@dyntell.com
Requires-Python: >=3.9,<4.0
Classifier: Programming Language :: Python :: 3
Classifier: Programming Language :: Python :: 3.9
Classifier: Programming Language :: Python :: 3.10
Classifier: Programming Language :: Python :: 3.11
